{
    "title":  "Battle Through the Heavens Season 5 Episode 25 Subtitle",
    "link":  "https://animexin.dev/battle-through-the-heavens-season-5-episode-25-subtitle/",
    "description":  "After three years of not seeing each other, Xiao Yan finally met Xun\u0027er at Jia Nan Academy. After that, they became closer and established the Stone Gate (Pan Gate).\n\nIn order to continue to improve his strength and avenge him on the Misty Cloud Sect, he risked continuing to go deeper into the Qi Refining Pagoda to devour the Fallen Heart Flame\n\nIndonesia\n\n\nSetelah tiga tahun tidak bertemu, Xiao Yan akhirnya bertemu Xun’er di Akademi Jia Nan . Setelah itu, mereka menjadi lebih dekat dan mendirikan Gerbang Batu (Gerbang Pan).\n\nUntuk terus meningkatkan kekuatannya dan membalaskan dendamnnya pada Sekte Misty Cloud, dia mengambil resiko terus masuk lebih dalam ke Pagoda Pemurnian Qi untuk melahap Api Hati Terjatuh (Fallen Heart Flame)",
    "mirrors":  [
                    {
                        "label":  "Hardsub English Ok.Ru",
                        "embedHtml":  "\u003ciframe width=\"560\" height=\"315\" src=\"//ok.ru/videoembed/4692197968436\" frameborder=\"0\" allow=\"autoplay\" allowfullscreen\u003e\u003c/iframe\u003e",
                        "embedUrl":  "https://ok.ru/videoembed/4692197968436",
                        "index":  1
                    },
                    {
                        "label":  "Hardsub Indonesia Ok.Ru",
                        "embedHtml":  "\u003ciframe width=\"560\" height=\"315\" src=\"//ok.ru/videoembed/4692197837364\" frameborder=\"0\" allow=\"autoplay\" allowfullscreen\u003e\u003c/iframe\u003e",
                        "embedUrl":  "https://ok.ru/videoembed/4692197837364",
                        "index":  2
                    },
                    {
                        "label":  "Hardsub Indonesia Daylimotion",
                        "embedHtml":  "\u003cdiv style=\"position:relative;padding-bottom:56.25%;height:0;overflow:hidden;\"\u003e\u003ciframe style=\"width:100%;height:100%;position:absolute;left:0px;top:0px;overflow:hidden\" frameborder=\"0\" type=\"text/html\" src=\"https://www.dailymotion.com/embed/video/k2fLYpOwWcWjBXyEb0D\" width=\"100%\" height=\"100%\"   allow=\"autoplay\" allowfullscreen\u003e\u003c/iframe\u003e\u003c/div\u003e",
                        "embedUrl":  "https://www.dailymotion.com/embed/video/k2fLYpOwWcWjBXyEb0D",
                        "index":  3
                    },
                    {
                        "label":  "Hardsub English Daylimotion",
                        "embedHtml":  "\u003cdiv style=\"position:relative;padding-bottom:56.25%;height:0;overflow:hidden;\"\u003e\u003ciframe style=\"width:100%;height:100%;position:absolute;left:0px;top:0px;overflow:hidden\" frameborder=\"0\" type=\"text/html\" src=\"https://www.dailymotion.com/embed/video/k4WC6NXVfSlc2jyEb0G\" width=\"100%\" height=\"100%\"   allow=\"autoplay\" allowfullscreen\u003e\u003c/iframe\u003e\u003c/div\u003e",
                        "embedUrl":  "https://www.dailymotion.com/embed/video/k4WC6NXVfSlc2jyEb0G",
                        "index":  4
                    },
                    {
                        "label":  "Hardsub Indonesia Terabox",
                        "embedHtml":  "\u003ciframe width=\"100%\" height=\"100%\"  frameborder=\"0\" src=\"https://terabox.com/sharing/embed?surl=vIGE4y5ao1qpSdIctyIohg\u0026resolution=720\u0026autoplay=true\u0026mute=false\u0026uk=4400255350575\u0026fid=902235727038093\" allowfullscreen\u003e\u003c/iframe\u003e",
                        "embedUrl":  "https://terabox.com/sharing/embed?surl=vIGE4y5ao1qpSdIctyIohg\u0026resolution=720\u0026autoplay=true\u0026mute=false\u0026uk=4400255350575\u0026fid=902235727038093",
                        "index":  5
                    },
                    {
                        "label":  "Hardsub English Terabox",
                        "embedHtml":  "\u003ciframe width=\"100%\" height=\"100%\"  frameborder=\"0\" src=\"https://terabox.com/sharing/embed?surl=ROk1d2JctoeC_x3fVMD5zw\u0026resolution=720\u0026autoplay=true\u0026mute=false\u0026uk=4400255350575\u0026fid=398429993079286\" allowfullscreen\u003e\u003c/iframe\u003e",
                        "embedUrl":  "https://terabox.com/sharing/embed?surl=ROk1d2JctoeC_x3fVMD5zw\u0026resolution=720\u0026autoplay=true\u0026mute=false\u0026uk=4400255350575\u0026fid=398429993079286",
                        "index":  6
                    },
                    {
                        "label":  "Hardsub Indonesia Dood",
                        "embedHtml":  "\u003ciframe width=\"600\" height=\"480\" src=\"https://dood.re/e/lr64y88jfd8fkr7k8jouc1yyb5yi98uh\" scrolling=\"no\" frameborder=\"0\" allowfullscreen=\"true\"\u003e\u003c/iframe\u003e\r\n",
                        "embedUrl":  "https://dood.re/e/lr64y88jfd8fkr7k8jouc1yyb5yi98uh",
                        "index":  7
                    },
                    {
                        "label":  "Hardsub english Dood",
                        "embedHtml":  "\u003ciframe width=\"600\" height=\"480\" src=\"https://dood.re/e/8r5c4zzhrzebpwan6iizmx8fysfihb4x\" scrolling=\"no\" frameborder=\"0\" allowfullscreen=\"true\"\u003e\u003c/iframe\u003e\r\n",
                        "embedUrl":  "https://dood.re/e/8r5c4zzhrzebpwan6iizmx8fysfihb4x",
                        "index":  8
                    },
                    {
                        "label":  "All Sub Player Daylimotion (have much ads from video player)",
                        "embedHtml":  "\u003cdiv style=\"position:relative;padding-bottom:56.25%;height:0;overflow:hidden;\"\u003e\u003ciframe style=\"width:100%;height:100%;position:absolute;left:0px;top:0px;overflow:hidden\" frameborder=\"0\" type=\"text/html\" src=\"https://www.dailymotion.com/embed/video/k54PmNeplMqYUOyEaed\" width=\"100%\" height=\"100%\"   allow=\"autoplay\" allowfullscreen\u003e\u003c/iframe\u003e\u003c/div\u003e",
                        "embedUrl":  "https://www.dailymotion.com/embed/video/k54PmNeplMqYUOyEaed",
                        "index":  9
                    },
                    {
                        "label":  "All Sub Player Dood",
                        "embedHtml":  "\u003ciframe width=\"600\" height=\"480\" src=\"https://dood.re/e/88rj75afu1g20twbuxkluwc1469utnkd\" scrolling=\"no\" frameborder=\"0\" allowfullscreen=\"true\"\u003e\u003c/iframe\u003e\r\n",
                        "embedUrl":  "https://dood.re/e/88rj75afu1g20twbuxkluwc1469utnkd",
                        "index":  10
                    },
                    {
                        "label":  "All Sub Player Fembed",
                        "embedHtml":  "\u003ccenter\u003e\u003ch2 style=\u0027font-size: 14px;margin: 10px 0;margin-top: 0;border-radius: 3px;background: #FDECEC;color: #B34037;text-shadow: 0 1px 1px #FFF;padding: 8px;border: 1px solid #F5C5C5;\u0027\u003eVideo Not Available\u003c/h2\u003e\u003c/center\u003e",
                        "embedUrl":  "",
                        "index":  11
                    },
                    {
                        "label":  "Portuguese",
                        "embedHtml":  "\u003ciframe src=\"//gdriveplayer.to/embed2.php?link=YuIYFZQz6LmKh8KJFDdy7gjdFq8%252FfdJz3hQDyWC3ou3ev%252FrRrB9p4TaWG20jvP1SVlWJlVtsxu9j4Kru1f2qKs0g8TVT4cQmCmaU3VUSb1GrQqY0Opd1Z0GmCqftpTqQyj0rNjSDNtdL%252F7YGrAVkHfP0ntl3HuoPszcCOpynhBRfoVyv%252BsGEPHbkKY68RWdsqyZ0MWKeP0MjOwnc%252F160Wqmi%252FAggQAnc%252BlN0cV85y96z5RTVWC81e%252FCoOTEqolbQ6PDKQtjvg3KU0tmaRqxKoVQd8zLQwO9vcCB%252FrN6HYMXsBFvkWBJFmHWJJYQDq7UGPjqwGQCdEZzmkOKMKhKEXPEYcn6RVVjH2%252Be3yU6adzPb5rgca0rZQ7nCsfpmHiZ%252B7fEp8witNppvSk%252F9Evbdub\" frameborder=\"0\" width=\"100%\" height=\"400\" allowfullscreen=\"allowfullscreen\"\u003e\u003c/iframe\u003e",
                        "embedUrl":  "https://gdriveplayer.to/embed2.php?link=YuIYFZQz6LmKh8KJFDdy7gjdFq8%252FfdJz3hQDyWC3ou3ev%252FrRrB9p4TaWG20jvP1SVlWJlVtsxu9j4Kru1f2qKs0g8TVT4cQmCmaU3VUSb1GrQqY0Opd1Z0GmCqftpTqQyj0rNjSDNtdL%252F7YGrAVkHfP0ntl3HuoPszcCOpynhBRfoVyv%252BsGEPHbkKY68RWdsqyZ0MWKeP0MjOwnc%252F160Wqmi%252FAggQAnc%252BlN0cV85y96z5RTVWC81e%252FCoOTEqolbQ6PDKQtjvg3KU0tmaRqxKoVQd8zLQwO9vcCB%252FrN6HYMXsBFvkWBJFmHWJJYQDq7UGPjqwGQCdEZzmkOKMKhKEXPEYcn6RVVjH2%252Be3yU6adzPb5rgca0rZQ7nCsfpmHiZ%252B7fEp8witNppvSk%252F9Evbdub",
                        "index":  12
                    },
                    {
                        "label":  "Turkish",
                        "embedHtml":  "\u003ciframe src=\"//gdriveplayer.to/embed2.php?link=FjmbEUfRhq1TNNV62YD5QAc9y0OsJj%252BuZG4UjowEGY%252FDLfUcOaeqP9sEwirETNsHic7%252FH93fWTs1xV0Dj2KqDImjCXKrCKxxOGBn77sPbnUqRWKbQGGkrK%252B7hcXceAX9hqpo17xNb35r0jqgTj3y8iQ%252BvtEb7U6%252FQsz9V2ABgC8NcwKIZKdBtEQ%252F7VNEV4WfDILWLSkr7U7F7gCrqXKIpxNFLjgBZwkJQMljWspb0pbuTMaoz8TwR81UrM8AQtLVGZ%252FGvRCjgXF6nx97nKX2270VkfwaLBIPaqHn3uo2fs0CGQoJtffJWDgvXYLVJyNhwMVMy5uvatzLsUfYQjrk3ovUDI6sVC2b3ox81c2daLJqsO0C5PhfLssep2NAVyUC9oSR7U%252FtMDi02zf%252ByjU%252Fv%252B\" frameborder=\"0\" width=\"100%\" height=\"400\" allowfullscreen=\"allowfullscreen\"\u003e\u003c/iframe\u003e",
                        "embedUrl":  "https://gdriveplayer.to/embed2.php?link=FjmbEUfRhq1TNNV62YD5QAc9y0OsJj%252BuZG4UjowEGY%252FDLfUcOaeqP9sEwirETNsHic7%252FH93fWTs1xV0Dj2KqDImjCXKrCKxxOGBn77sPbnUqRWKbQGGkrK%252B7hcXceAX9hqpo17xNb35r0jqgTj3y8iQ%252BvtEb7U6%252FQsz9V2ABgC8NcwKIZKdBtEQ%252F7VNEV4WfDILWLSkr7U7F7gCrqXKIpxNFLjgBZwkJQMljWspb0pbuTMaoz8TwR81UrM8AQtLVGZ%252FGvRCjgXF6nx97nKX2270VkfwaLBIPaqHn3uo2fs0CGQoJtffJWDgvXYLVJyNhwMVMy5uvatzLsUfYQjrk3ovUDI6sVC2b3ox81c2daLJqsO0C5PhfLssep2NAVyUC9oSR7U%252FtMDi02zf%252ByjU%252Fv%252B",
                        "index":  13
                    },
                    {
                        "label":  "Spanish",
                        "embedHtml":  "\u003ciframe src=\"//gdriveplayer.to/embed2.php?link=RcdN1BfbIk6cA%252Bl1Ju3H0wTPfkcZNrATzKeTSms%252BOyWyuk6swfyp1kTC5Zm2ImnQUVbgbYLcEnqWs5vRqICOd%252BEtcUgns8OtUc2hsQX8lmRT3hjJcHbT4JZqN9MNxYueXSR6hKlZhwKyNR3L0V30yPJGlW7IhBtvk6w7S9VVDZYuszff82ef%252BN4%252FfP0BrFxofDvGx4qDp6P7zS2FmY1V4bL19HluOt%252Bg1hu%252BIzWF9hZdfc8z3v6dUdPX29nHgky2htCu1M99FiK7XmSOS7QPeKxdNHIeiql8eh8%252Btvdaq5DdYjXOzvWvyUvViIWf8p8gKUWkb8Nst5MZCHiwCxIJO%252BIHVcu3xYWTXIzpJWLzBlPrUK%252Bhz%252BCPl2lOeypeO7ExsMMObUCX4RBG3N811iBzaO\" frameborder=\"0\" width=\"100%\" height=\"400\" allowfullscreen=\"allowfullscreen\"\u003e\u003c/iframe\u003e",
                        "embedUrl":  "https://gdriveplayer.to/embed2.php?link=RcdN1BfbIk6cA%252Bl1Ju3H0wTPfkcZNrATzKeTSms%252BOyWyuk6swfyp1kTC5Zm2ImnQUVbgbYLcEnqWs5vRqICOd%252BEtcUgns8OtUc2hsQX8lmRT3hjJcHbT4JZqN9MNxYueXSR6hKlZhwKyNR3L0V30yPJGlW7IhBtvk6w7S9VVDZYuszff82ef%252BN4%252FfP0BrFxofDvGx4qDp6P7zS2FmY1V4bL19HluOt%252Bg1hu%252BIzWF9hZdfc8z3v6dUdPX29nHgky2htCu1M99FiK7XmSOS7QPeKxdNHIeiql8eh8%252Btvdaq5DdYjXOzvWvyUvViIWf8p8gKUWkb8Nst5MZCHiwCxIJO%252BIHVcu3xYWTXIzpJWLzBlPrUK%252Bhz%252BCPl2lOeypeO7ExsMMObUCX4RBG3N811iBzaO",
                        "index":  14
                    },
                    {
                        "label":  "Italian",
                        "embedHtml":  "\u003ciframe src=\"//gdriveplayer.to/embed2.php?link=ZfJIoscVN4iHY9Ve1Tm07AoWBqAgf0s%252BU90f9aaB75pTVrLV28iz7JRP6%252FRCK4%252Bk1u%252B5HqBrwdVvh0i6cEu8rotX%252FCmUZGESWLYiWLsAPyeLYfy1%252BpLmbSJHwprIam3vw1nru2wOPseK1ZXCoftAUZOC%252FZxNJEpyS2UBjgZQJEokYnLt9FmKMxhfMXCfNqFqV4pgv1WzMZyNKduP5dKdbsYhvD9UsDl%252FjF9XLw5FIyYAZIPETp%252FUFlijS7O6tcxT1byHXDcMSpn4YucJH%252FAIm5QngdgiYBvtLMB7wd6iukzPCeXfw1sHX0bslOXy0VlmYU8ENGLE3f6aFdrZTeWfcnl60uA0ha9ZLIR6OSCYI7%252B%252BNhC%252BjVpDvYU2epikCBJkv2h5KV6GMgima%252BvK4y8RhQ\" frameborder=\"0\" width=\"100%\" height=\"400\" allowfullscreen=\"allowfullscreen\"\u003e\u003c/iframe\u003e",
                        "embedUrl":  "https://gdriveplayer.to/embed2.php?link=ZfJIoscVN4iHY9Ve1Tm07AoWBqAgf0s%252BU90f9aaB75pTVrLV28iz7JRP6%252FRCK4%252Bk1u%252B5HqBrwdVvh0i6cEu8rotX%252FCmUZGESWLYiWLsAPyeLYfy1%252BpLmbSJHwprIam3vw1nru2wOPseK1ZXCoftAUZOC%252FZxNJEpyS2UBjgZQJEokYnLt9FmKMxhfMXCfNqFqV4pgv1WzMZyNKduP5dKdbsYhvD9UsDl%252FjF9XLw5FIyYAZIPETp%252FUFlijS7O6tcxT1byHXDcMSpn4YucJH%252FAIm5QngdgiYBvtLMB7wd6iukzPCeXfw1sHX0bslOXy0VlmYU8ENGLE3f6aFdrZTeWfcnl60uA0ha9ZLIR6OSCYI7%252B%252BNhC%252BjVpDvYU2epikCBJkv2h5KV6GMgima%252BvK4y8RhQ",
                        "index":  15
                    },
                    {
                        "label":  "Polish",
                        "embedHtml":  "\u003ciframe src=\"//gdriveplayer.to/embed2.php?link=cjStd91hik34oYYjRqMWnQEtwnEy2PNyXIx2bcg4H8ZS4OQp6wRQ50kobSF3QaOHDvfu84jWfpLTyR5EC4233RwzC2lreelzwi%252BbK8V14UCqK4A7dVUSElo4BWNNVSoREYd22QIHKuUEYep1%252FvyHzLuH9NooX%252Bqq0%252BKpxexed2tkL0DbbQgkvuYl6018ehhl3EAvIsTXqoRSGa8YIg2N%252BGBv%252BrpdzT6HsmCReMgWuNI%252FDNr62jpO2NBe6CravbEh4UdOQ3lUTmxEaoGfuwP%252BtCkITVLSMeNqROBD9jqTeGndN%252Bz6m4v5iZ3IkMFFM9%252B8d%252FUvpc7OpgfL4%252BjiXZIfe4UoP9MYz%252Fo4WttOeQvvOtT%252FeYjOmmIKDItgxgfW%252FtUE7BDzSrAdtOzHy0wB%252BTMmiz\" frameborder=\"0\" width=\"100%\" height=\"400\" allowfullscreen=\"allowfullscreen\"\u003e\u003c/iframe\u003e",
                        "embedUrl":  "https://gdriveplayer.to/embed2.php?link=cjStd91hik34oYYjRqMWnQEtwnEy2PNyXIx2bcg4H8ZS4OQp6wRQ50kobSF3QaOHDvfu84jWfpLTyR5EC4233RwzC2lreelzwi%252BbK8V14UCqK4A7dVUSElo4BWNNVSoREYd22QIHKuUEYep1%252FvyHzLuH9NooX%252Bqq0%252BKpxexed2tkL0DbbQgkvuYl6018ehhl3EAvIsTXqoRSGa8YIg2N%252BGBv%252BrpdzT6HsmCReMgWuNI%252FDNr62jpO2NBe6CravbEh4UdOQ3lUTmxEaoGfuwP%252BtCkITVLSMeNqROBD9jqTeGndN%252Bz6m4v5iZ3IkMFFM9%252B8d%252FUvpc7OpgfL4%252BjiXZIfe4UoP9MYz%252Fo4WttOeQvvOtT%252FeYjOmmIKDItgxgfW%252FtUE7BDzSrAdtOzHy0wB%252BTMmiz",
                        "index":  16
                    }
                ],
    "downloads":  [
                      {
                          "label":  "Terabox",
                          "url":  "https://terabox.com/s/1-wy7O5X73_ypssw38m-LVg",
                          "language":  "Subtitle Indonesia"
                      },
                      {
                          "label":  "Mirror",
                          "url":  "https://www.mirrored.to/files/1QNWKGWS/AnimeXinax.,com_btth_s5_ep_25_indo.mp4_links",
                          "language":  "Subtitle Indonesia"
                      },
                      {
                          "label":  "Mediafire",
                          "url":  "https://www.mediafire.com/file/yo04rrgfdfjgbj7/AnimeXinax.%252Ccom_btth_s5_ep_25_indo.mp4/file",
                          "language":  "Subtitle Indonesia"
                      },
                      {
                          "label":  "Terabox",
                          "url":  "https://terabox.com/s/1uKuXtJvNGlCRIXq3KIid4g",
                          "language":  "Subtitle English"
                      },
                      {
                          "label":  "Mirror",
                          "url":  "https://www.mirrored.to/files/KZO7EHYR/AnimeXinax.,com_btth_s5_ep_25_eng.mp4_links",
                          "language":  "Subtitle English"
                      },
                      {
                          "label":  "Mediafire",
                          "url":  "https://www.mediafire.com/file/pqtl4cf7t8kjta4/AnimeXinax.%252Ccom_btth_s5_ep_25_eng.mp4/file",
                          "language":  "Subtitle English"
                      }
                  ]
}