{
    "title":  "Supreme God Emperor Episode 234 Subtitle",
    "link":  "https://animexin.dev/supreme-god-emperor-episode-234-subtitle/",
    "description":  "",
    "mirrors":  [
                    {
                        "label":  "Hardsub English Ok.Ru",
                        "embedHtml":  "\u003ciframe width=\"560\" height=\"315\" src=\"//ok.ru/videoembed/4662669085236\" frameborder=\"0\" allow=\"autoplay\" allowfullscreen\u003e\u003c/iframe\u003e",
                        "embedUrl":  "https://ok.ru/videoembed/4662669085236",
                        "index":  1
                    },
                    {
                        "label":  "Hardsub Indonesia Ok.Ru",
                        "embedHtml":  "\u003ciframe width=\"560\" height=\"315\" src=\"//ok.ru/videoembed/4662669150772\" frameborder=\"0\" allow=\"autoplay\" allowfullscreen\u003e\u003c/iframe\u003e",
                        "embedUrl":  "https://ok.ru/videoembed/4662669150772",
                        "index":  2
                    },
                    {
                        "label":  "Hardsub Indonesia Daylimotion",
                        "embedHtml":  "\u003cdiv style=\"position:relative;padding-bottom:56.25%;height:0;overflow:hidden;\"\u003e\u003ciframe style=\"width:100%;height:100%;position:absolute;left:0px;top:0px;overflow:hidden\" frameborder=\"0\" type=\"text/html\" src=\"https://www.dailymotion.com/embed/video/k2qjXiEik4aS6tyCVOZ\" width=\"100%\" height=\"100%\"   allow=\"autoplay\" allowfullscreen\u003e\u003c/iframe\u003e\u003c/div\u003e",
                        "embedUrl":  "https://www.dailymotion.com/embed/video/k2qjXiEik4aS6tyCVOZ",
                        "index":  3
                    },
                    {
                        "label":  "Hardsub English Daylimotion",
                        "embedHtml":  "\u003cdiv style=\"position:relative;padding-bottom:56.25%;height:0;overflow:hidden;\"\u003e\u003ciframe style=\"width:100%;height:100%;position:absolute;left:0px;top:0px;overflow:hidden\" frameborder=\"0\" type=\"text/html\" src=\"https://www.dailymotion.com/embed/video/k5tUBI09LVxpYzyCVOY\" width=\"100%\" height=\"100%\"   allow=\"autoplay\" allowfullscreen\u003e\u003c/iframe\u003e\u003c/div\u003e",
                        "embedUrl":  "https://www.dailymotion.com/embed/video/k5tUBI09LVxpYzyCVOY",
                        "index":  4
                    },
                    {
                        "label":  "Hardsub Indonesia Terabox",
                        "embedHtml":  "\u003ciframe width=\"100%\" height=\"100%\"  frameborder=\"0\" src=\"https://terabox.com/sharing/embed?surl=1weOTWWt4ULaisiyKlwfVg\u0026resolution=1080\u0026autoplay=true\u0026mute=false\u0026uk=4400255350575\u0026fid=504427590770502\" allowfullscreen\u003e\u003c/iframe\u003e",
                        "embedUrl":  "https://terabox.com/sharing/embed?surl=1weOTWWt4ULaisiyKlwfVg\u0026resolution=1080\u0026autoplay=true\u0026mute=false\u0026uk=4400255350575\u0026fid=504427590770502",
                        "index":  5
                    },
                    {
                        "label":  "Hardsub English Terabox",
                        "embedHtml":  "\u003ciframe width=\"100%\" height=\"100%\"  frameborder=\"0\" src=\"https://terabox.com/sharing/embed?surl=3pFKnpLrS4QOR_e3TyUr7Q\u0026resolution=1080\u0026autoplay=true\u0026mute=false\u0026uk=4400255350575\u0026fid=123094568025985\" allowfullscreen\u003e\u003c/iframe\u003e",
                        "embedUrl":  "https://terabox.com/sharing/embed?surl=3pFKnpLrS4QOR_e3TyUr7Q\u0026resolution=1080\u0026autoplay=true\u0026mute=false\u0026uk=4400255350575\u0026fid=123094568025985",
                        "index":  6
                    },
                    {
                        "label":  "Hardsub Indonesia Dood",
                        "embedHtml":  "\u003ciframe width=\"600\" height=\"480\" src=\"https://dood.re/e/ry9a7jn2tirw0xnnjynwx4ib61tlblqp\" scrolling=\"no\" frameborder=\"0\" allowfullscreen=\"true\"\u003e\u003c/iframe\u003e\r\n",
                        "embedUrl":  "https://dood.re/e/ry9a7jn2tirw0xnnjynwx4ib61tlblqp",
                        "index":  7
                    },
                    {
                        "label":  "Hardsub english Dood",
                        "embedHtml":  "\u003ciframe width=\"600\" height=\"480\" src=\"https://dood.re/e/00z8j2aemf2f707fndhwftpdpib70t1y\" scrolling=\"no\" frameborder=\"0\" allowfullscreen=\"true\"\u003e\u003c/iframe\u003e\r\n",
                        "embedUrl":  "https://dood.re/e/00z8j2aemf2f707fndhwftpdpib70t1y",
                        "index":  8
                    },
                    {
                        "label":  "All Sub Player Daylimotion (have much ads from video player)",
                        "embedHtml":  "\u003cdiv style=\"position:relative;padding-bottom:56.25%;height:0;overflow:hidden;\"\u003e\u003ciframe style=\"width:100%;height:100%;position:absolute;left:0px;top:0px;overflow:hidden\" frameborder=\"0\" type=\"text/html\" src=\"https://www.dailymotion.com/embed/video/kHQsCI9yGGoY8qyCVcA\" width=\"100%\" height=\"100%\"   allow=\"autoplay\" allowfullscreen\u003e\u003c/iframe\u003e\u003c/div\u003e",
                        "embedUrl":  "https://www.dailymotion.com/embed/video/kHQsCI9yGGoY8qyCVcA",
                        "index":  9
                    },
                    {
                        "label":  "All Sub Player Dood",
                        "embedHtml":  "\u003ciframe width=\"600\" height=\"480\" src=\"https://dood.re/e/hoa87nktx5kwm4jgojgv0ajrwe15yhu8\" scrolling=\"no\" frameborder=\"0\" allowfullscreen=\"true\"\u003e\u003c/iframe\u003e\r\n",
                        "embedUrl":  "https://dood.re/e/hoa87nktx5kwm4jgojgv0ajrwe15yhu8",
                        "index":  10
                    },
                    {
                        "label":  "All Sub Player Fembed",
                        "embedHtml":  "\u003ciframe width=\"560\" height=\"315\" src=\"https://www.fembed.com/v/001gj1ilrr7jpw-1\" frameborder=\"0\" allowfullscreen\u003e\u003c/iframe\u003e\r\n\r\n",
                        "embedUrl":  "https://www.fembed.com/v/001gj1ilrr7jpw-1",
                        "index":  11
                    },
                    {
                        "label":  "Portuguese",
                        "embedHtml":  "\u003ciframe src=\"//gdriveplayer.to/embed2.php?link=JCf2a6ZkG0I4pByWdweuCAXKENlvz9ORrj9%252F4iMjh9WrkTybhBYjIeyC3eggfYNvdmm0kJLr25y0oYpvGi8u%252FouD0USHLNxjusFJ%252BE6i37sDt4CCiqh3nypIEEPcY%252BqucxqOKdArMWHLmbZylZcP0Ypu79GNSiw2SC6ddhdN0HoTftCuvlW6XqDjNGHlyRtLywFGr%252FbfZ7SxVk4Am3TCv7GtK1aUqNw9Gln7CzwF%252BUWyHh%252BBwTXmNImO1fsXaZFVIlt%252F7in6T3BXSpxFF9rzfPtCZ28oyxeJDYPMOyLWzz5Msq5g7D%252B7T2qhON%252BT41sHPHwVg9dukiR%252FCTpIvTxdQOOH9Is9ucluAWnec%252BUDbbn0zAotuhKWXxpJRQaf5a7hA6G3s6tgPzk2irK69%252FlgxG\" frameborder=\"0\" width=\"100%\" height=\"400\" allowfullscreen=\"allowfullscreen\"\u003e\u003c/iframe\u003e",
                        "embedUrl":  "https://gdriveplayer.to/embed2.php?link=JCf2a6ZkG0I4pByWdweuCAXKENlvz9ORrj9%252F4iMjh9WrkTybhBYjIeyC3eggfYNvdmm0kJLr25y0oYpvGi8u%252FouD0USHLNxjusFJ%252BE6i37sDt4CCiqh3nypIEEPcY%252BqucxqOKdArMWHLmbZylZcP0Ypu79GNSiw2SC6ddhdN0HoTftCuvlW6XqDjNGHlyRtLywFGr%252FbfZ7SxVk4Am3TCv7GtK1aUqNw9Gln7CzwF%252BUWyHh%252BBwTXmNImO1fsXaZFVIlt%252F7in6T3BXSpxFF9rzfPtCZ28oyxeJDYPMOyLWzz5Msq5g7D%252B7T2qhON%252BT41sHPHwVg9dukiR%252FCTpIvTxdQOOH9Is9ucluAWnec%252BUDbbn0zAotuhKWXxpJRQaf5a7hA6G3s6tgPzk2irK69%252FlgxG",
                        "index":  12
                    },
                    {
                        "label":  "Turkish",
                        "embedHtml":  "\u003ciframe src=\"//gdriveplayer.to/embed2.php?link=8qWmgNM4dfMfStLYVtt50wyWN%252BmwEi8%252BWm0XMuIfMYTwtA861FTOBp%252Be3pyzjTrMOUxHojgV%252BFw2KlWPX1kNKxIuy5nZesK40ALUX9ksdYn39r%252Bz%252BhvypfhvIpf5rZwYl5G%252Bh2Jw9ist60U12gZ2xKeeHHU0XT1%252F2bxZzisBOY8sY%252F0N1Cq50jDEZfd0%252FZfJ36BO2K%252B6ynwbRu5xukFqPb6JdvkA2FdaX3oq%252ByrTIn2IZWpgE071MjliSq3xf1pm7cGNcSr0SQQ7gwxytA6nhiALaiyqoIxKL2d1ICT39kYqjcK7P3TLVel%252Fwy8hS%252B%252FG72qXfDqZfu6ZkB5dDkCrnvtvLRbYYtN0uqvAAtWSyyjuGyB%252BA8qFRQCwANJdz3LMa0Y38vtSgPKpxtTIlHA8vu\" frameborder=\"0\" width=\"100%\" height=\"400\" allowfullscreen=\"allowfullscreen\"\u003e\u003c/iframe\u003e",
                        "embedUrl":  "https://gdriveplayer.to/embed2.php?link=8qWmgNM4dfMfStLYVtt50wyWN%252BmwEi8%252BWm0XMuIfMYTwtA861FTOBp%252Be3pyzjTrMOUxHojgV%252BFw2KlWPX1kNKxIuy5nZesK40ALUX9ksdYn39r%252Bz%252BhvypfhvIpf5rZwYl5G%252Bh2Jw9ist60U12gZ2xKeeHHU0XT1%252F2bxZzisBOY8sY%252F0N1Cq50jDEZfd0%252FZfJ36BO2K%252B6ynwbRu5xukFqPb6JdvkA2FdaX3oq%252ByrTIn2IZWpgE071MjliSq3xf1pm7cGNcSr0SQQ7gwxytA6nhiALaiyqoIxKL2d1ICT39kYqjcK7P3TLVel%252Fwy8hS%252B%252FG72qXfDqZfu6ZkB5dDkCrnvtvLRbYYtN0uqvAAtWSyyjuGyB%252BA8qFRQCwANJdz3LMa0Y38vtSgPKpxtTIlHA8vu",
                        "index":  13
                    },
                    {
                        "label":  "Spanish",
                        "embedHtml":  "\u003ciframe src=\"//gdriveplayer.to/embed2.php?link=OmOFKKPI%252Be4R4nkQm5SWfQPCTIXysSpdK%252FINFHZ498CX7T4uIq35gpyARaDnawLt%252FIH7BBb7XBPBGTe1ECbznXUbGOL153Fe5vrjBw5do8hr08uMnYL5mhOmkSQ8X0%252BXiukNfJX24UD1dG5VtGHIN9NalKFe7t2%252FsWxmWotn9D22MsIAhqRgL1fCfzu8zo%252FnvVuZda%252F4HcxqCq5Qk8FIoPexVX%252FduQ1hBDKPxKVF5YMunqoSTzu%252BJx6%252FCnZzRaXSnhFQ1Nft7ZqSRHfGqFNX%252BTRXatqBkT%252FZkorJDV2fAgRSh7X9m1eNoAFkx5A7Xg27D%252BEIu33TV8p0sBHgJfy2XEs1QfXlik7JDurqActGF1oCW0bFIzXvQFSFQZDrCtrdgXyLHOuuLx1lNsBlv9Uu1b\" frameborder=\"0\" width=\"100%\" height=\"400\" allowfullscreen=\"allowfullscreen\"\u003e\u003c/iframe\u003e",
                        "embedUrl":  "https://gdriveplayer.to/embed2.php?link=OmOFKKPI%252Be4R4nkQm5SWfQPCTIXysSpdK%252FINFHZ498CX7T4uIq35gpyARaDnawLt%252FIH7BBb7XBPBGTe1ECbznXUbGOL153Fe5vrjBw5do8hr08uMnYL5mhOmkSQ8X0%252BXiukNfJX24UD1dG5VtGHIN9NalKFe7t2%252FsWxmWotn9D22MsIAhqRgL1fCfzu8zo%252FnvVuZda%252F4HcxqCq5Qk8FIoPexVX%252FduQ1hBDKPxKVF5YMunqoSTzu%252BJx6%252FCnZzRaXSnhFQ1Nft7ZqSRHfGqFNX%252BTRXatqBkT%252FZkorJDV2fAgRSh7X9m1eNoAFkx5A7Xg27D%252BEIu33TV8p0sBHgJfy2XEs1QfXlik7JDurqActGF1oCW0bFIzXvQFSFQZDrCtrdgXyLHOuuLx1lNsBlv9Uu1b",
                        "index":  14
                    },
                    {
                        "label":  "Italian",
                        "embedHtml":  "\u003ciframe src=\"//gdriveplayer.to/embed2.php?link=cyvWVgXi6ROVhOIJgpHu3QoTwpkQQln1hROCDEW%252FFvHncesp2xqSy9gI206n4zbn8eP%252BRAzYkJ6xthv1ZyYwh2b4Vq2A3ftqOF9QJQeuICu0bICJD7hy2tKJaZt8Iei5xr4xfYHHsJy7yLj0Y%252FuYzZuNQhtv8imRjAnC%252B2IucaF1Lu3OaOxSbOYRlixSD%252BFYkIynR8EWZbmnmVAU7%252BwDHdvJNG5RMdsXWZ4oJlx99pZ3y%252Fv4EaUqz7DRVxQSu%252FLWsLVAgL9Zk%252Fl8zPWCNrLnhMvjsHC%252BGQG5%252BSfPlGpDjuisF8z9M%252BzdcSFwEFTop8lIATu1oX4O89ztKJoPg1qRli4O1Fr7d3vKuudF%252BbmMg8rbodMkezdzAjtsCVW52B%252F7B85wqme1eACNIo14i%252BdsUL\" frameborder=\"0\" width=\"100%\" height=\"400\" allowfullscreen=\"allowfullscreen\"\u003e\u003c/iframe\u003e",
                        "embedUrl":  "https://gdriveplayer.to/embed2.php?link=cyvWVgXi6ROVhOIJgpHu3QoTwpkQQln1hROCDEW%252FFvHncesp2xqSy9gI206n4zbn8eP%252BRAzYkJ6xthv1ZyYwh2b4Vq2A3ftqOF9QJQeuICu0bICJD7hy2tKJaZt8Iei5xr4xfYHHsJy7yLj0Y%252FuYzZuNQhtv8imRjAnC%252B2IucaF1Lu3OaOxSbOYRlixSD%252BFYkIynR8EWZbmnmVAU7%252BwDHdvJNG5RMdsXWZ4oJlx99pZ3y%252Fv4EaUqz7DRVxQSu%252FLWsLVAgL9Zk%252Fl8zPWCNrLnhMvjsHC%252BGQG5%252BSfPlGpDjuisF8z9M%252BzdcSFwEFTop8lIATu1oX4O89ztKJoPg1qRli4O1Fr7d3vKuudF%252BbmMg8rbodMkezdzAjtsCVW52B%252F7B85wqme1eACNIo14i%252BdsUL",
                        "index":  15
                    },
                    {
                        "label":  "Polish",
                        "embedHtml":  "\u003ciframe src=\"//gdriveplayer.to/embed2.php?link=cV5lKLsYDD9tBBMAT%252FcyRAZ8pFBln7D%252FozVO8BoCB%252F0qk8oiHJAKHNlaF14KEKBXRMgKI5%252F%252BQ7xRMMmhQmzrWwT7CiSsWt2woy%252Bk2S2s4KQ2ixM7HL6hJ%252B7sQziaC6hKUDBpk8fQFJ2ON3WO6qdRy2IMhoxK1Wrynl%252F3o0ZYZ8Hs6UOf0b1FkcRvOUpLOWbPMux%252BGkmeRv2qrcqIB8urXfRzmUm3iivvJpkOfDtNzzHqucpMbsIg2EwmQ0fNqBAIh14qli4UdAIFM5XvSOTzwXVwhzvU9A6LQmIgsv7M1PYPwfvLNDaYq72gTS0FqaH%252BD2945jfQShch6wbhu6QgSgpLVqzF1rZ89fQkw3XpoPMWPjc1ouQLG8RyJl4keP%252BEsiaEYZhc9RDnGOXFJL%252BTwL\" frameborder=\"0\" width=\"100%\" height=\"400\" allowfullscreen=\"allowfullscreen\"\u003e\u003c/iframe\u003e",
                        "embedUrl":  "https://gdriveplayer.to/embed2.php?link=cV5lKLsYDD9tBBMAT%252FcyRAZ8pFBln7D%252FozVO8BoCB%252F0qk8oiHJAKHNlaF14KEKBXRMgKI5%252F%252BQ7xRMMmhQmzrWwT7CiSsWt2woy%252Bk2S2s4KQ2ixM7HL6hJ%252B7sQziaC6hKUDBpk8fQFJ2ON3WO6qdRy2IMhoxK1Wrynl%252F3o0ZYZ8Hs6UOf0b1FkcRvOUpLOWbPMux%252BGkmeRv2qrcqIB8urXfRzmUm3iivvJpkOfDtNzzHqucpMbsIg2EwmQ0fNqBAIh14qli4UdAIFM5XvSOTzwXVwhzvU9A6LQmIgsv7M1PYPwfvLNDaYq72gTS0FqaH%252BD2945jfQShch6wbhu6QgSgpLVqzF1rZ89fQkw3XpoPMWPjc1ouQLG8RyJl4keP%252BEsiaEYZhc9RDnGOXFJL%252BTwL",
                        "index":  16
                    }
                ],
    "downloads":  [
                      {
                          "label":  "Terabox",
                          "url":  "https://terabox.com/s/1w-7BY1L4ncusq87SngKAEQ",
                          "language":  "Subtitle Indonesia"
                      },
                      {
                          "label":  "Terabox",
                          "url":  "https://terabox.com/s/1edWVTVxRyQx5kaN_wg6EOA",
                          "language":  "Subtitle English"
                      }
                  ]
}